[
  {
    "id": 0,
    "origin": 0,
    "destination": 1,
    "q_k": 1,
    "desired_departure_min": 57.2316731518673,
    "desired_arrival_min": 58.7316731518673,
    "slack_min": 20.0,
    "tau_sp_min": 1.5,
    "T_k_min": [
      57.2316731518673,
      78.7316731518673
    ],
    "T_in_min": [
      57.2316731518673,
      67.2316731518673
    ],
    "T_out_min": [
      58.7316731518673,
      78.7316731518673
    ]
  },
  {
    "id": 1,
    "origin": 4,
    "destination": 3,
    "q_k": 1,
    "desired_departure_min": 39.81247517217221,
    "desired_arrival_min": 41.31247517217221,
    "slack_min": 20.0,
    "tau_sp_min": 1.5,
    "T_k_min": [
      39.81247517217221,
      61.31247517217221
    ],
    "T_in_min": [
      39.81247517217221,
      49.81247517217221
    ],
    "T_out_min": [
      41.31247517217221,
      61.31247517217221
    ]
  },
  {
    "id": 2,
    "origin": 2,
    "destination": 6,
    "q_k": 1,
    "desired_departure_min": 51.43484436178783,
    "desired_arrival_min": 57.43484436178783,
    "slack_min": 20.0,
    "tau_sp_min": 6.0,
    "T_k_min": [
      51.43484436178783,
      77.43484436178784
    ],
    "T_in_min": [
      51.43484436178783,
      61.43484436178783
    ],
    "T_out_min": [
      57.43484436178783,
      77.43484436178784
    ]
  },
  {
    "id": 3,
    "origin": 8,
    "destination": 5,
    "q_k": 1,
    "desired_departure_min": 30.47251192772097,
    "desired_arrival_min": 31.97251192772097,
    "slack_min": 20.0,
    "tau_sp_min": 1.5,
    "T_k_min": [
      30.47251192772097,
      51.97251192772097
    ],
    "T_in_min": [
      30.47251192772097,
      40.47251192772097
    ],
    "T_out_min": [
      31.97251192772097,
      51.97251192772097
    ]
  },
  {
    "id": 4,
    "origin": 4,
    "destination": 0,
    "q_k": 2,
    "desired_departure_min": 24.388966665773747,
    "desired_arrival_min": 27.388966665773747,
    "slack_min": 20.0,
    "tau_sp_min": 3.0,
    "T_k_min": [
      24.388966665773747,
      47.38896666577375
    ],
    "T_in_min": [
      24.388966665773747,
      34.38896666577375
    ],
    "T_out_min": [
      27.388966665773747,
      47.38896666577375
    ]
  },
  {
    "id": 5,
    "origin": 5,
    "destination": 6,
    "q_k": 1,
    "desired_departure_min": 57.90622910810118,
    "desired_arrival_min": 62.40622910810118,
    "slack_min": 20.0,
    "tau_sp_min": 4.5,
    "T_k_min": [
      57.90622910810118,
      82.40622910810117
    ],
    "T_in_min": [
      57.90622910810118,
      67.90622910810117
    ],
    "T_out_min": [
      62.40622910810118,
      82.40622910810117
    ]
  },
  {
    "id": 6,
    "origin": 2,
    "destination": 8,
    "q_k": 1,
    "desired_departure_min": 15.450379182387074,
    "desired_arrival_min": 18.450379182387074,
    "slack_min": 20.0,
    "tau_sp_min": 3.0,
    "T_k_min": [
      15.450379182387074,
      38.450379182387074
    ],
    "T_in_min": [
      15.450379182387074,
      25.450379182387074
    ],
    "T_out_min": [
      18.450379182387074,
      38.450379182387074
    ]
  },
  {
    "id": 7,
    "origin": 2,
    "destination": 5,
    "q_k": 1,
    "desired_departure_min": 34.94641850851724,
    "desired_arrival_min": 36.44641850851724,
    "slack_min": 20.0,
    "tau_sp_min": 1.5,
    "T_k_min": [
      34.94641850851724,
      56.44641850851724
    ],
    "T_in_min": [
      34.94641850851724,
      44.94641850851724
    ],
    "T_out_min": [
      36.44641850851724,
      56.44641850851724
    ]
  },
  {
    "id": 8,
    "origin": 5,
    "destination": 8,
    "q_k": 2,
    "desired_departure_min": 12.45627953238539,
    "desired_arrival_min": 13.95627953238539,
    "slack_min": 20.0,
    "tau_sp_min": 1.5,
    "T_k_min": [
      12.45627953238539,
      33.95627953238539
    ],
    "T_in_min": [
      12.45627953238539,
      22.456279532385388
    ],
    "T_out_min": [
      13.95627953238539,
      33.95627953238539
    ]
  },
  {
    "id": 9,
    "origin": 7,
    "destination": 6,
    "q_k": 2,
    "desired_departure_min": 62.101665017982924,
    "desired_arrival_min": 63.601665017982924,
    "slack_min": 20.0,
    "tau_sp_min": 1.5,
    "T_k_min": [
      62.101665017982924,
      83.60166501798292
    ],
    "T_in_min": [
      62.101665017982924,
      72.10166501798292
    ],
    "T_out_min": [
      63.601665017982924,
      83.60166501798292
    ]
  }
]